CHANGELOG.md
LICENSE
README.md
sn3218/__init__.py
sn3218-3.0.0.dist-info/METADATA
sn3218-3.0.0.dist-info/WHEEL
sn3218-3.0.0.dist-info/licenses/LICENSE
sn3218-3.0.0.dist-info/RECORD
